botframework/connector/__init__.py
botframework/connector/_configuration.py
botframework/connector/_not_implemented_http_client.py
botframework/connector/about.py
botframework/connector/aiohttp_bf_pipeline.py
botframework/connector/bot_framework_sdk_client_async.py
botframework/connector/channels.py
botframework/connector/connector_client.py
botframework/connector/emulator_api_client.py
botframework/connector/http_client_base.py
botframework/connector/http_client_factory.py
botframework/connector/http_request.py
botframework/connector/http_response_base.py
botframework/connector/version.py
botframework/connector/aio/__init__.py
botframework/connector/aio/_connector_client_async.py
botframework/connector/aio/operations_async/__init__.py
botframework/connector/aio/operations_async/_attachments_operations_async.py
botframework/connector/aio/operations_async/_conversations_operations_async.py
botframework/connector/async_mixin/__init__.py
botframework/connector/async_mixin/async_mixin.py
botframework/connector/auth/__init__.py
botframework/connector/auth/_bot_framework_client_impl.py
botframework/connector/auth/_built_in_bot_framework_authentication.py
botframework/connector/auth/_connector_factory_impl.py
botframework/connector/auth/_government_cloud_bot_framework_authentication.py
botframework/connector/auth/_parameterized_bot_framework_authentication.py
botframework/connector/auth/_public_cloud_bot_framework_authentication.py
botframework/connector/auth/_user_token_client_impl.py
botframework/connector/auth/app_credentials.py
botframework/connector/auth/authenticate_request_result.py
botframework/connector/auth/authentication_configuration.py
botframework/connector/auth/authentication_constants.py
botframework/connector/auth/bot_framework_authentication.py
botframework/connector/auth/bot_framework_authentication_factory.py
botframework/connector/auth/certificate_app_credentials.py
botframework/connector/auth/channel_provider.py
botframework_connector-4.15.1.dist-info/METADATA
botframework_connector-4.15.1.dist-info/WHEEL
botframework_connector-4.15.1.dist-info/top_level.txt
botframework_connector-4.15.1.dist-info/RECORD
