Metadata-Version: 2.1
Name: botframework-connector
Version: 4.15.1
Summary: Microsoft Bot Framework Bot Builder SDK for Python.
Home-page: https://www.github.com/Microsoft/botbuilder-python
Author: Microsoft
License: MIT
Keywords: BotFrameworkConnector,bots,ai,botframework,botbuilder
Platform: UNKNOWN
Classifier: Programming Language :: Python :: 3.7
Classifier: Intended Audience :: Developers
Classifier: License :: OSI Approved :: MIT License
Classifier: Operating System :: OS Independent
Classifier: Development Status :: 5 - Production/Stable
Classifier: Topic :: Scientific/Engineering :: Artificial Intelligence
Requires-Dist: msrest ==0.7.*
Requires-Dist: PyJWT >=2.4.0
Requires-Dist: botbuilder-schema ==4.15.1
Requires-Dist: msal ==1.*
